Workbook

Sheet README
A1: SA BEVERAGES — THE AUTONOMOUS BOARDROOM | Debate Dataset (Phase 4 input)
A3: This workbook holds the labelled transcripts and evaluation scores for both debates.
A4: It is the input to the Phase 4 Python/NLP pipeline.
A6: SHEETS:
A7: Transcripts — one row per speaker turn. Columns: turn_id, debate_level, round,
A8: turn_order (position within round), speaker_role, archetype, turn_note,
A9: text (raw, unedited), word_count (auto-calculated).
A10: Scores — one row per evaluator x criterion (1-10) with the one-line verdict.
A11: Score_Summary — average score per evaluator and overall (auto-calculated).
A13: debate_level values:
A14: Top-Management (Phase 2) — the autonomous 5-persona boardroom debate (added).
A15: Middle-Management (Phase 3) — the human-led Product Head cascade (added; Product Head turns written by the student).
... A19: cleaning happens inside the Python notebook so the original evidence is preserved.

Sheet Transcripts
A1: turn_id | B1: debate_level | C1: round | D1: turn_order | E1: speaker_role | F1: archetype | G1: turn_note | H1: text | I1: word_count
A2: 1 | B2: Top-Management (Phase 2) | C2: 1 | D2: 1 | E2: CEO | F2: The Visionary Balancer | G2: Opening | H2: Colleagues, read the curve. Twenty-five percent growth became eight percent in a single year. One franchise partner, one season, one category — that is not a company, that is an exposure. Savories is our growth engine, not a side project. We already own the hardest asset in Indian FMCG: millions of outlets that open their shutters for us daily. Snacks is a ₹40,000-crore-plus category compounding double digits. I am not asking whether we diversify. I am asking how fast. Do nothing, and we manage a beautiful, dignified decline. | I2: =LEN(TRIM(H2))-LEN(SUBSTITUTE(TRIM(H2)," ",""))+1 -> 88
A3: 2 | B3: Top-Management (Phase 2) | C3: 1 | D3: 2 | E3: CMO | F3: The Brand Custodian | H3: With respect, CEO, the shopper doesn't read our balance sheet. She knows us as a cold drink she trusts on a hot afternoon. Ask her to buy a baked namkeen from that same brand and watch the hesitation. We have equity, not permission. Haldiram owns taste heritage; we own refreshment. I want Savories built with a distinct identity, a parent endorsement at most, and proof of pull before we spend a rupee on national media. Give me two test markets, trial and repeat data. No validation, no launch. | I3: =LEN(TRIM(H3))-LEN(SUBSTITUTE(TRIM(H3)," ",""))+1 -> 88
A4: 3 | B4: Top-Management (Phase 2) | C4: 1 | D4: 3 | E4: CFO | F4: The Profit Sentinel | H4: Numbers, please. Our core earns twenty-three percent operating margin. Packaged snacks earns eight to twelve, after Haldiram, Balaji, Bikaji and Lay's have finished bleeding each other on price. So the proposal is to spend capex on baking lines and a brand build to buy lower-quality revenue. Show me payback under four years, ROCE above cost of capital, and a cash-burn ceiling. I will fund Phase One only: ring-fenced, staged, with written kill-criteria. Open-ended ambition on my balance sheet is not strategy. It is margin dilution with a slogan. | I4: =LEN(TRIM(H4))-LEN(SUBSTITUTE(TRIM(H4)," ",""))+1 -> 88
A5: 4 | B5: Top-Management (Phase 2) | C5: 1 | D5: 4 | E5: COO | F5: The Ground Reality Engine | H5: Bottling is not baking. Different ovens, different ingredients, different suppliers, different wastage profile. And the distribution synergy everyone celebrates is unproven: my routes are built for heavy, high-velocity crates, not light, bulky, crush-prone ambient packs that eat shelf space and return as damages. Different shelf life, different merchandising, and no chilled cabinet to hide behind. Give me a validated co-manufacturer for eighteen months before we touch capex, a quality-control protocol, and a ramp-up plan that does not touch core OTIF. Break service levels on beverages for a snack pilot, and I will stop it myself. | I5: =LEN(TRIM(H5))-LEN(SUBSTITUTE(TRIM(H5)," ",""))+1 -> 95
A6: 5 | B6: Top-Management (Phase 2) | C6: 1 | D6: 5 | E6: CTO | F6: The System Architect | H6: Two hard problems, calmly stated. First, formulation: baked, low-oil, multigrain and genuinely tasty is not a marketing claim, it is eighteen to twenty-four months of iteration, and India rejects bland. Second, regime change: FSSAI food-safety compliance, allergen control, nutrition labelling and batch traceability are nothing like beverage QC. We also lack food scientists; that talent market is thin and expensive. I will not ship an unvalidated recipe or compress a compliance runway. Give me R&D hires, a stage-gated product roadmap, and I will build the traceability and D2C stack alongside it. | I6: =LEN(TRIM(H6))-LEN(SUBSTITUTE(TRIM(H6)," ",""))+1 -> 91
A7: 6 | B7: Top-Management (Phase 2) | C7: 1 | D7: 6 | E7: CEO | F7: The Visionary Balancer | G7: Closing Strategy | H7: Heard. Every condition you named is a design constraint, not a veto. So: Savories launches asset-light through a vetted co-packer, not new plants. Phase One is capped, ring-fenced, and killable. CMO gets two lead markets before national media. CTO gets a stage-gated recipe with compliance built in, not bolted on. COO's core OTIF is untouchable. But understand the clock: every quarter we deliberate, Haldiram and Bikaji take shelf space we will later rent back at a premium. Direction is settled. We are negotiating pace, not permission. | I7: =LEN(TRIM(H7))-LEN(SUBSTITUTE(TRIM(H7)," ",""))+1 -> 86
A8: 7 | B8: Top-Management (Phase 2) | C8: 2 | D8: 1 | E8: CEO | F8: The Visionary Balancer | H8: Let me put numbers against your fears. Target: eight percent of group revenue from new categories within three years. Savories is the wedge, not the whole portfolio. CFO, I am asking for a capped Phase One, not a blank cheque. CMO, distinct sub-brand, endorsed quietly. COO, co-packer first, own line only after volumes justify it. CTO, stage-gates with real money behind R&D. Now cross-examine me properly — but bring me alternatives, not only objections. What is your plan for the eight-percent core? | I8: =LEN(TRIM(H8))-LEN(SUBSTITUTE(TRIM(H8)," ",""))+1 -> 82
A9: 8 | B9: Top-Management (Phase 2) | C9: 2 | D9: 2 | E9: CMO | F9: The Brand Custodian | H9: Then answer the blind spot. Eight percent of revenue from snacks in three years means roughly ₹1,700 crore — in a category where trial is cheap and repeat is brutal. Better-for-you namkeen is a premium urban niche; mass India buys taste and grammage. Which is it? If premium, my media spend per consumer triples and modern trade plus quick-commerce listing fees will eat the phasing. Also: if Savories fails publicly, distributors question our judgement on the core. Fund insight and a pilot properly, or expect vanity trial and no repeat. | I9: =LEN(TRIM(H9))-LEN(SUBSTITUTE(TRIM(H9)," ",""))+1 -> 90
A10: 9 | B10: Top-Management (Phase 2) | C10: 2 | D10: 3 | E10: CFO | F10: The Profit Sentinel | H10: ₹1,700 crore of snack revenue at ten percent contribution replaces ₹170 crore of profit we could earn by pushing ₹740 crore through the core at twenty-three. That is the real trade-off, and nobody has priced it. Co-packing protects capex but caps gross margin at commodity levels. Quick-commerce listing fees, trade schemes and damages are not phasing, they are permanent leakage. My terms: Phase One capped at ₹150 crore over eighteen months, quarterly gates, kill if repeat rate misses target twice. No dilution of core capex. Say yes, or find another CFO. | I10: =LEN(TRIM(H10))-LEN(SUBSTITUTE(TRIM(H10)," ",""))+1 -> 91
A11: 10 | B11: Top-Management (Phase 2) | C11: 2 | D11: 4 | E11: COO | F11: The Ground Reality Engine | H11: Co-packer first — agreed, that is the only sane route. But understand what you just bought. Co-packers in namkeen run other people's brands on the same lines; I get third priority in festive season, allergen cross-contamination risk, and no control over oil quality. Ambient snacks also break my route economics: a crate of bottles earns more per cubic foot than twenty snack packs. So either we pay distributors a separate margin slab, or they hide Savories under the counter. And I want secondary sales visibility before you call this synergy. | I11: =LEN(TRIM(H11))-LEN(SUBSTITUTE(TRIM(H11)," ",""))+1 -> 90
A12: 11 | B12: Top-Management (Phase 2) | C12: 2 | D12: 5 | E12: CTO | F12: The System Architect | H12: Three gates, then. Gate one: six months, twelve formulations, blind taste tests against Haldiram baked and Too Yumm — we proceed only if we win on taste, not on nutrition claims. Gate two: FSSAI licensing, allergen mapping, shelf-life accelerated testing at co-packer sites; audited, not assumed. Gate three: traceability by batch and a D2C stack for early repeat data, which answers the CMO cheaply. But compressing eighteen months into nine gives you a product that tastes like cardboard and a recall risk. I can be fast or I can be safe. | I12: =LEN(TRIM(H12))-LEN(SUBSTITUTE(TRIM(H12)," ",""))+1 -> 91
A13: 12 | B13: Top-Management (Phase 2) | C13: 2 | D13: 6 | E13: CEO | F13: The Visionary Balancer | G13: Closing Strategy | H13: Then here is the negotiated shape. Phase One: ₹150 crore, eighteen months, quarterly gates, CFO holds the kill-switch. CTO's taste gate is absolute — we do not launch a product that loses a blind test. CMO gets Maharashtra and NCR as lead markets with a distinct Savories identity, parent endorsed in small type. COO gets a separate snack margin slab for distributors and secondary-sales dashboards funded by CTO's stack. What I will not phase is intent. Eighteen months buys evidence; it does not buy us permission to retreat. | I13: =LEN(TRIM(H13))-LEN(SUBSTITUTE(TRIM(H13)," ",""))+1 -> 88
A14: 13 | B14: Top-Management (Phase 2) | C14: 3 | D14: 1 | E14: CEO | F14: The Visionary Balancer | H14: Final check. The mandate stands: Savories enters as our beachhead into savoury snacks, asset-light, gated, and funded to win — not to dabble. I have conceded pace, capital, and sequencing. I will not concede direction, because the alternative is an eight-percent-growth company renting its future from one franchise partner. Tell me plainly: are you aligned and accountable for your gate, or are you recording dissent? I want owners, not observers. Half-hearted execution will kill this faster than any competitor in Nagpur or Bikaner. | I14: =LEN(TRIM(H14))-LEN(SUBSTITUTE(TRIM(H14)," ",""))+1 -> 83
A15: 14 | B15: Top-Management (Phase 2) | C15: 3 | D15: 2 | E15: CMO | F15: The Brand Custodian | H15: Aligned — conditionally, and I will own it. Savories gets its own logo, its own voice, and a whisper of the parent, so a failure stays contained. I take Maharashtra and NCR, and I report trial, repeat and weighted distribution every quarter, honestly. My ultimatum is simple: if repeat purchase misses forty percent by month twelve, we do not buy our way to national launch with media. That is not caution, it is respect for a brand three decades in the making. Give me the pilot, and I will give you pull. | I15: =LEN(TRIM(H15))-LEN(SUBSTITUTE(TRIM(H15)," ",""))+1 -> 92
A16: 15 | B16: Top-Management (Phase 2) | C16: 3 | D16: 3 | E16: CFO | F16: The Profit Sentinel | H16: Aligned, with the kill-switch in writing. ₹150 crore, ring-fenced, off the core's capex line, released in four tranches against gates. Board reviews quarterly; two consecutive misses on repeat rate or contribution margin and we stop, write off, and say so publicly without sentiment. No topping up from beverage cash flows mid-cycle. If those conditions hold, I support the direction and will defend it to investors as disciplined optionality. If they are quietly loosened in month nine, my support ends that day. Discipline is the only reason this is fundable. | I16: =LEN(TRIM(H16))-LEN(SUBSTITUTE(TRIM(H16)," ",""))+1 -> 89
A17: 16 | B17: Top-Management (Phase 2) | C17: 3 | D17: 4 | E17: COO | F17: The Ground Reality Engine | H17: Conditionally aligned. Co-packer route, two vetted partners for redundancy, audited quarterly by CTO's team. Separate margin slab for distributors, separate secondary-sales tracking, and snacks ride existing routes only where crate economics allow — elsewhere we appoint snack-specific sub-stockists. Hard line: core beverage OTIF stays above ninety-six percent. If Savories volumes start cannibalising my festive-season truck space or my depot shelf, I escalate to the board immediately, not politely. Execute it this way and it is feasible. Rush it, and you will get stockouts in the core and stale packs in the trade. | I17: =LEN(TRIM(H17))-LEN(SUBSTITUTE(TRIM(H17)," ",""))+1 -> 92
A18: 17 | B18: Top-Management (Phase 2) | C18: 3 | D18: 5 | E18: CTO | F18: The System Architect | H18: Aligned, and I will sign for the gates. Six months to a blind-test-winning formulation, food scientists hired within ninety days, FSSAI licensing and allergen protocols running parallel from day one, not retrofitted. Batch traceability live before the first commercial pallet moves. D2C storefront in month seven gives us clean repeat data months before general trade reports it. My single non-negotiable: no launch on a recipe that loses its taste test, however loudly the calendar argues. A compliance failure in food does not cost margin. It costs the licence to operate. | I18: =LEN(TRIM(H18))-LEN(SUBSTITUTE(TRIM(H18)," ",""))+1 -> 90
A19: 18 | B19: Top-Management (Phase 2) | C19: 3 | D19: 6 | E19: CEO | F19: The Visionary Balancer | G19: Closing Strategy / Mandate (Phase 3 input) | H19: Executive order, minuted. One: Savories proceeds as a distinct, parent-endorsed sub-brand, co-manufactured by two audited partners. Two: Phase One capped at ₹150 crore, eighteen months, four tranches, CFO's kill-switch binding. Three: CTO's taste and compliance gates are absolute; no gate, no launch. Four: Maharashtra and NCR lead markets, forty percent repeat by month twelve as the go-national trigger. Five: core OTIF ninety-six percent is inviolable, snack margin slab approved. We reconvene in ninety days. Colleagues — we are not leaving beverages. We are refusing to be only beverages. | I19: =LEN(TRIM(H19))-LEN(SUBSTITUTE(TRIM(H19)," ",""))+1 -> 88
A20: 19 | B20: Middle-Management (Phase 3) | C20: 1 | D20: 1 | E20: Sales | F20: Regional Sales & Distribution Manager | H20: Boss, the mandate is clear, and Maharashtra plus NCR is the right battleground for me. But let's talk shelves. My beverage distributors run crate routes; snacks need hanger displays, frequent small drops and different beat plans. Will the approved margin slab reach distributors before launch, or after? Without it, they'll bury Savories behind fast-moving SKUs. I also need clarity on whether I get dedicated snack sub-stockists or must load existing routes, because loading existing routes risks core OTIF. And forty percent repeat by month twelve means weighted distribution must be locked by month three. | I20: =LEN(TRIM(H20))-LEN(SUBSTITUTE(TRIM(H20)," ",""))+1 -> 94
A21: 20 | B21: Middle-Management (Phase 3) | C21: 1 | D21: 2 | E21: Brand | F21: Brand & Marketing Manager — Savories | H21: I'm energised by the distinct sub-brand call, but the ₹150-crore cap is shared across four tranches, and I don't yet know my slice. Building awareness from zero in two markets while chasing forty percent repeat means sampling-heavy, not TV-heavy. I need to know: what is my Tranche One marketing envelope, and which KPIs unlock Tranche Two? Also, quick-commerce listings cost money upfront; is that my budget or Sales'? And every pack claim, even "crunchier", must clear compliance first, so I need a fixed claim-review turnaround from R&D before creative locks. | I21: =LEN(TRIM(H21))-LEN(SUBSTITUTE(TRIM(H21)," ",""))+1 -> 90
A22: 21 | B22: Middle-Management (Phase 3) | C22: 1 | D22: 3 | E22: Supply Chain | F22: Supply Chain & Co-Packer Manager | H22: Noted: core OTIF at ninety-six percent is inviolable, and I'll protect it. My concern is sequencing. Shortlisting, auditing and onboarding two co-packers, including allergen controls and line trials, realistically takes four to five months. Festive season is when co-packers prioritise bigger clients, so I need capacity commitments written into contracts, not promises. Ambient snacks also crush easily; our beverage trucks and warehouses weren't designed for them, so damages could spike. I'm requesting a ring-fenced snack logistics lane and a clear escalation rule: if snacks and core compete for a truck, core wins, automatically. | I22: =LEN(TRIM(H22))-LEN(SUBSTITUTE(TRIM(H22)," ",""))+1 -> 93
A23: 22 | B23: Middle-Management (Phase 3) | C23: 1 | D23: 4 | E23: R&D | F23: R&D / Product & Compliance Lead | H23: I welcome the absolute gates; they protect everyone. But let me be precise about time. Six months to a blind-test-winning formulation is aggressive when I don't yet have the food scientists. Hiring two or three within ninety days in this market is uncertain, so I need approval for interim consultants now. FSSAI labelling, allergen declarations and co-packer traceability cannot be compressed; any shortcut risks recall. Supply Chain's co-packer audits and my formulation trials must run in parallel, not sequence. And to be clear: if a recipe fails the taste gate, I will not sign it off, regardless of launch dates. | I23: =LEN(TRIM(H23))-LEN(SUBSTITUTE(TRIM(H23)," ",""))+1 -> 100
A24: 23 | B24: Middle-Management (Phase 3) | C24: 1 | D24: 5 | E24: Product Head | F24: Product Head (Human) | G24: Human-written | H24: Thank you — these are legitimate execution concerns, and I'll address each. Sales: the margin slab will reach distributors before launch, and you will have dedicated snack sub-stockists in both markets, so core beats and OTIF remain protected. Brand: your tranche-one budget is ring-fenced, quick-commerce sits within your allocation, and tranche two unlocks on trial and repeat. Supply chain: festive-season capacity will be written into the co-packer contracts, and if snacks and core compete for a truck, core takes priority automatically. R&D: interim consultants are approved immediately, trials run parallel to audits, and the gates remain absolute. Sequencing is next. | I24: =LEN(TRIM(H24))-LEN(SUBSTITUTE(TRIM(H24)," ",""))+1 -> 100
A25: 24 | B25: Middle-Management (Phase 3) | C25: 2 | D25: 1 | E25: Sales | F25: Regional Sales & Distribution Manager | H25: Appreciated, boss. The pre-launch slab and dedicated sub-stockists solve my biggest worry. Now the hard part: who funds sub-stockist onboarding, their credit period and display hangers, my trade budget or Brand's? And timing: if R&D clears the taste gate at month six and co-packers need five months, my first dispatch lands around month seven. That leaves roughly five months to earn forty percent repeat. Can the repeat clock start from first secondary sale instead of mandate date? Also, Brand's sampling calendar must sync with my beat plan, otherwise trial happens where stock isn't. | I25: =LEN(TRIM(H25))-LEN(SUBSTITUTE(TRIM(H25)," ",""))+1 -> 93
A26: 25 | B26: Middle-Management (Phase 3) | C26: 2 | D26: 2 | E26: Brand | F26: Brand & Marketing Manager — Savories | H26: Ring-fenced is good, but I need a number, not a principle. Sampling at scale, quick-commerce listing fees and launch creative could consume most of tranche one before a single repeat purchase shows. So here's my question: trial and repeat unlock tranche two, but if the CFO's kill-switch reviews run on calendar dates and launch slips to month seven, do those reviews slip too? Otherwise I'm judged on a market I've barely entered. And R&D still hasn't committed a claim-review turnaround. I'm proposing five working days, because creative can't lock without it. | I26: =LEN(TRIM(H26))-LEN(SUBSTITUTE(TRIM(H26)," ",""))+1 -> 91
A27: 26 | B27: Middle-Management (Phase 3) | C27: 2 | D27: 3 | E27: Supply Chain | F27: Supply Chain & Co-Packer Manager | H27: Contract clauses and the core-first rule help, thank you. But you didn't address my ring-fenced snack logistics lane. Without dedicated ambient-snack warehouse space and proper stacking norms, damages will eat Sales' margins. Second, the hand-off: R&D's final recipe determines line specs, packaging film and shelf life, and co-packers can't finalise line trials until that's frozen. I need a recipe-freeze date, even provisional, by month four. Third, the dedicated sub-stockists need their own dispatch schedule. Who owns the forecast feeding my production plan, Sales or Brand? One owner, one number, please. | I27: =LEN(TRIM(H27))-LEN(SUBSTITUTE(TRIM(H27)," ",""))+1 -> 90
A28: 27 | B28: Middle-Management (Phase 3) | C28: 2 | D28: 4 | E28: R&D | F28: R&D / Product & Compliance Lead | H28: Consultants approved, thank you; that buys time. But Supply Chain wants a recipe freeze by month four, and my blind tests need at least two iteration cycles, which realistically lands at month five. Can we agree month four for base formulation and packaging format, with seasoning tweaks allowed until month five? On Brand's request, five working days for claim review is feasible only if claims arrive with substantiation data attached; unsupported claims restart the clock. Also, consultants shouldn't sign our FSSAI dossiers. Who's the accountable signatory until permanent hires join? I need that named before trials begin. | I28: =LEN(TRIM(H28))-LEN(SUBSTITUTE(TRIM(H28)," ",""))+1 -> 97
A29: 28 | B29: Middle-Management (Phase 3) | C29: 2 | D29: 5 | E29: Product Head | F29: Product Head (Human) | G29: Human-written | H29: Understood — decisions. Sales: sub-stockist onboarding and hangers come from trade budget, sampling from Brand; and yes, the repeat clock starts at first secondary sale, not mandate date. Brand: your tranche-one envelope is fixed today at forty percent of the tranche, and kill-switch reviews track months-in-market, not the calendar — you won't be judged on a market you haven't entered. Supply chain: the dedicated ambient lane is approved; Sales owns the single demand forecast. R&D: freeze base formulation and format at month four, seasoning to month five; five-day claim review holds when substantiation is attached; you remain accountable signatory, consultants support only. | I29: =LEN(TRIM(H29))-LEN(SUBSTITUTE(TRIM(H29)," ",""))+1 -> 102
A30: 29 | B30: Middle-Management (Phase 3) | C30: 3 | D30: 1 | E30: Sales | F30: Regional Sales & Distribution Manager | H30: Aligned, with one condition. Trade budget covering onboarding and hangers, Brand funding sampling, and a repeat clock that starts at first secondary sale make this workable. Since I own the single forecast, I'll publish one monthly number, locked by the fifteenth, for Supply Chain. My remaining risk is on paper, not on the ground: the board set forty percent repeat "by month twelve." I need the revised clock minuted with the CFO and board, or I'll be judged against two different dates. Once that's in writing, I'll start appointing sub-stockists in both markets this quarter. | I30: =LEN(TRIM(H30))-LEN(SUBSTITUTE(TRIM(H30)," ",""))+1 -> 95
A31: 30 | B31: Middle-Management (Phase 3) | C31: 3 | D31: 2 | E31: Brand | F31: Brand & Marketing Manager — Savories | H31: Aligned. Forty percent of tranche one is a real number, and months-in-market reviews make the kill-switch fair. I'll build a sampling-first plan synced to Sales' beat plan and send every claim to R&D with substantiation attached. One flag, not a blocker: if launch lands at month seven and reviews track months-in-market, the eighteen-month Phase One window may not cover twelve full months in market. Can Finance confirm how the timeline, the cap and the review schedule fit together? Otherwise, I'm ready to brief agencies next week. | I31: =LEN(TRIM(H31))-LEN(SUBSTITUTE(TRIM(H31)," ",""))+1 -> 86
A32: 31 | B32: Middle-Management (Phase 3) | C32: 3 | D32: 3 | E32: Supply Chain | F32: Supply Chain & Co-Packer Manager | H32: Aligned. The ambient lane, the core-first rule, the contractual capacity clauses and a single forecast owner close my main gaps. A base-formulation freeze at month four gives co-packers enough time for line trials and packaging film. My remaining risk is speed, not policy: auditing two co-packers in four to five months leaves almost no buffer. I'll start shortlisting this week and run audits in parallel with R&D trials. If one partner fails its audit, I need pre-approval to fast-track a backup instead of waiting for the ninety-day reconvene. | I32: =LEN(TRIM(H32))-LEN(SUBSTITUTE(TRIM(H32)," ",""))+1 -> 88
A33: 32 | B33: Middle-Management (Phase 3) | C33: 3 | D33: 4 | E33: R&D | F33: R&D / Product & Compliance Lead | H33: Aligned, with one resourcing risk. A base freeze at month four and seasoning at month five are workable, and I accept accountability as signatory. However, until the hires close, I'll be signing FSSAI dossiers while also leading formulation, blind tests and co-packer traceability, with consultants only supporting. That stretches me thin. I need hiring treated as a priority and a clear escalation path if food-scientist roles stay open beyond ninety days. The gates remain non-negotiable: if a recipe fails the blind test, launch waits. With that understood, I'm ready to begin trials. | I33: =LEN(TRIM(H33))-LEN(SUBSTITUTE(TRIM(H33)," ",""))+1 -> 92
A34: 33 | B34: Middle-Management (Phase 3) | C34: 3 | D34: 5 | E34: Product Head | F34: Product Head (Human) | G34: Human-written / Closing | H34: Then we're aligned, and the mandate stands. Closing commitments: I'll have the revised repeat clock — first secondary sale — minuted with the CFO and board this week, so no one is judged against two dates, and I'll ask Finance to reconcile the eighteen-month cap with twelve months in market in the same note. Supply chain, you have pre-approval to fast-track a vetted backup if a co-packer fails its audit — don't wait for the reconvene. R&D, hiring is now a board-level priority with a named escalation path past ninety days. Gates stay absolute. Start this quarter. Thank you. | I34: =LEN(TRIM(H34))-LEN(SUBSTITUTE(TRIM(H34)," ",""))+1 -> 99

Sheet Scores
A1: debate_level | B1: evaluator_role | C1: archetype | D1: criterion_code | E1: criterion | F1: score (1-10) | G1: verdict
A2: Top-Management (Phase 2) | B2: CMO | C2: The Brand Custodian | D2: a | E2: Relevance to department needs | F2: 8 | G2: The pilot-first, distinct-identity structure is exactly the protection the parent brand needed.
A3: Top-Management (Phase 2) | B3: CMO | C3: The Brand Custodian | D3: b | E3: Practical knowledge/feasibility | F3: 7 | G3: He understands distribution, but still underestimates how expensive shopper conversion in snacks really is.
A4: Top-Management (Phase 2) | B4: CMO | C4: The Brand Custodian | D4: c | E4: Novelty of approach | F4: 6 | G4: Leveraging our outlet reach is smart; a baked better-for-you namkeen is crowded, not original.
A5: Top-Management (Phase 2) | B5: CMO | C5: The Brand Custodian | D5: d | E5: Implementation timeline realism | F5: 6 | G5: Eighteen months to evidence is fair; three years to ₹1,700 crore is marketing fantasy.
A6: Top-Management (Phase 2) | B6: CMO | C6: The Brand Custodian | D6: e | E6: Potential overall success | F6: 7 | G6: With a real pilot and honest repeat data, this can work — if we resist the urge to go national early.
A7: Top-Management (Phase 2) | B7: CFO | C7: The Profit Sentinel | D7: a | E7: Relevance to department needs | F7: 6 | G7: The capped, tranched structure respects capital discipline; the profit-substitution maths remains unpriced.
A8: Top-Management (Phase 2) | B8: CFO | C8: The Profit Sentinel | D8: b | E8: Practical knowledge/feasibility | F8: 6 | G8: Asset-light co-packing is financially literate, but commodity gross margins were accepted too casually.
A9: Top-Management (Phase 2) | B9: CFO | C9: The Profit Sentinel | D9: c | E9: Novelty of approach | F9: 5 | G9: Every maturing FMCG major makes this exact bet; novelty is not a line item anyway.
A10: Top-Management (Phase 2) | B10: CFO | C10: The Profit Sentinel | D10: d | E10: Implementation timeline realism | F10: 5 | G10: Payback inside four years is unproven and will slip the moment listing fees land.
A11: Top-Management (Phase 2) | B11: CFO | C11: The Profit Sentinel | D11: e | E11: Potential overall success | F11: 6 | G11: Fundable as staged optionality, dangerous the day the kill-switch becomes negotiable.
A12: Top-Management (Phase 2) | B12: COO | C12: The Ground Reality Engine | D12: a | E12: Relevance to department needs | F12: 6 | G12: Co-packer-first and the OTIF guarantee address my hardest constraints; route economics still hand-waved.
A13: Top-Management (Phase 2) | B13: COO | C13: The Ground Reality Engine | D13: b | E13: Practical knowledge/feasibility | F13: 5 | G13: The 'distribution synergy' remains an assumption dressed up as an asset until secondary data proves it.
... A41: Middle-Management (Phase 3) | B41: R&D | C41: R&D / Product & Compliance Lead | D41: e | E41: Change-readiness / team buy-in | F41: 8 | G41: Board-level hiring priority is reassuring, though I'll believe the escalation path when it has a named person.

Sheet Score_Summary
A1: Debate | B1: Evaluator | C1: Average score (1-10)
A2: Top-Management (Phase 2) | B2: CMO | C2: =AVERAGEIFS(Scores!$F$2:$F$41,Scores!$A$2:$A$41,A2,Scores!$B$2:$B$41,B2) -> 6.8
A3: Top-Management (Phase 2) | B3: CFO | C3: =AVERAGEIFS(Scores!$F$2:$F$41,Scores!$A$2:$A$41,A3,Scores!$B$2:$B$41,B3) -> 5.6
A4: Top-Management (Phase 2) | B4: COO | C4: =AVERAGEIFS(Scores!$F$2:$F$41,Scores!$A$2:$A$41,A4,Scores!$B$2:$B$41,B4) -> 5.6
A5: Top-Management (Phase 2) | B5: CTO | C5: =AVERAGEIFS(Scores!$F$2:$F$41,Scores!$A$2:$A$41,A5,Scores!$B$2:$B$41,B5) -> 6.4
A6: Top-Management (Phase 2) | B6: OVERALL | C6: =AVERAGEIFS(Scores!$F$2:$F$41,Scores!$A$2:$A$41,A6) -> 6.1
A7: Middle-Management (Phase 3) | B7: Sales | C7: =AVERAGEIFS(Scores!$F$2:$F$41,Scores!$A$2:$A$41,A7,Scores!$B$2:$B$41,B7) -> 8.2
A8: Middle-Management (Phase 3) | B8: Brand | C8: =AVERAGEIFS(Scores!$F$2:$F$41,Scores!$A$2:$A$41,A8,Scores!$B$2:$B$41,B8) -> 8
A9: Middle-Management (Phase 3) | B9: Supply Chain | C9: =AVERAGEIFS(Scores!$F$2:$F$41,Scores!$A$2:$A$41,A9,Scores!$B$2:$B$41,B9) -> 7.6
A10: Middle-Management (Phase 3) | B10: R&D | C10: =AVERAGEIFS(Scores!$F$2:$F$41,Scores!$A$2:$A$41,A10,Scores!$B$2:$B$41,B10) -> 7.4
A11: Middle-Management (Phase 3) | B11: OVERALL | C11: =AVERAGEIFS(Scores!$F$2:$F$41,Scores!$A$2:$A$41,A11) -> 7.8
